asciidoc3/BUGS.txt
asciidoc3/CHANGELOG
asciidoc3/CHANGELOG.txt
asciidoc3/COPYING
asciidoc3/COPYRIGHT
asciidoc3/INSTALL
asciidoc3/LICENSE
asciidoc3/README.md
asciidoc3/UNINSTALL
asciidoc3/a2x3.py
asciidoc3/asciidoc3.conf
asciidoc3/asciidoc3.py
asciidoc3/asciidoc3_postinstall.py
asciidoc3/asciidoc3api.py
asciidoc3/docbook45.conf
asciidoc3/docbook51.conf
asciidoc3/help.conf
asciidoc3/html4.conf
asciidoc3/html5.conf
asciidoc3/lang-cs.conf
asciidoc3/lang-de.conf
asciidoc3/lang-el.conf
asciidoc3/lang-en.conf
asciidoc3/lang-es.conf
asciidoc3/lang-fr.conf
asciidoc3/lang-hu.conf
asciidoc3/lang-it.conf
asciidoc3/lang-ja.conf
asciidoc3/lang-nl.conf
asciidoc3/lang-pt-BR.conf
asciidoc3/lang-ro.conf
asciidoc3/lang-ru.conf
asciidoc3/lang-se.conf
asciidoc3/lang-uk.conf
asciidoc3/lang-zh-CN.conf
asciidoc3/latex.conf
asciidoc3/setup.py
asciidoc3/slidy.conf
asciidoc3/text.conf
asciidoc3/xhtml11.conf
asciidoc3/dblatex/asciidoc3-dblatex.sty
asciidoc3/dblatex/asciidoc3-dblatex.xsl
asciidoc3/dblatex/dblatex-readme.txt
asciidoc3/doc/a2x3.1.gz
asciidoc3/doc/a2x3.1.txt
asciidoc3/doc/article-docinfo.xml
asciidoc3/doc/article.txt
asciidoc3/doc/article_docbook51-docinfo.xml
asciidoc3/doc/article_docbook51.txt
asciidoc3/doc/asciidoc3.1.gz
asciidoc3/doc/asciidoc3.1.txt
asciidoc3/doc/asciidoc3.conf
asciidoc3/doc/asciidoc3api.txt
asciidoc3/doc/asciimathml.txt
asciidoc3/doc/book-multi.txt
asciidoc3/doc/book-multi_docbook51.txt
asciidoc3/doc/book.txt
asciidoc3/doc/book_containing_an_abstract.txt
asciidoc3/doc/cheatsheet.txt
asciidoc3/doc/customers.csv
asciidoc3/doc/epub-notes.txt
asciidoc3/doc/faq.txt
asciidoc3/doc/latex-backend.txt
asciidoc3/doc/latex-bugs.txt
asciidoc3/doc/latex-filter.txt
asciidoc3/doc/latexmath.txt
asciidoc3/doc/latexmathml.txt
asciidoc3/doc/music-filter.txt
asciidoc3/doc/publishing-ebooks-with-asciidoc3.txt
asciidoc3/doc/quickstart.txt
asciidoc3/doc/readme.txt
asciidoc3/doc/readme_docbook51.txt
asciidoc3/doc/slidy-example.txt
asciidoc3/doc/slidy.txt
asciidoc3-3.2.1.dist-info/COPYING
asciidoc3-3.2.1.dist-info/LICENSE
asciidoc3-3.2.1.dist-info/METADATA
asciidoc3-3.2.1.dist-info/WHEEL
asciidoc3-3.2.1.dist-info/entry_points.txt
asciidoc3-3.2.1.dist-info/top_level.txt
asciidoc3-3.2.1.dist-info/RECORD
