Metadata-Version: 2.1
Name: asciidoc3
Version: 3.2.1
Summary: AsciiDoc3 Python3 GNU/Linux Windows AsciiDoc - see https://asciidoc3.org/pypi.html BEFORE installing
Home-page: https://asciidoc3.org
Author: Berthold Gehrke
Author-email: berthold.gehrke@gmail.com
License: GPLv2+
Project-URL: Source, https://gitlab.com/asciidoc3/asciidoc3
Project-URL: Funding, https://asciidoc3.org/contact.html
Keywords: text,markup,Windows,asciidoc,asciidoc3,python3
Platform: UNKNOWN
Classifier: Topic :: Text Processing
Classifier: Topic :: Text Processing :: Markup
Classifier: License :: OSI Approved :: GNU General Public License v2 or later (GPLv2+)
Classifier: Natural Language :: English
Classifier: Operating System :: POSIX
Classifier: Operating System :: Microsoft :: Windows
Classifier: Programming Language :: Python
Classifier: Programming Language :: Python :: 3 :: Only
Classifier: Programming Language :: Python :: 3.6
Classifier: Programming Language :: Python :: 3.7
Classifier: Programming Language :: Python :: 3.8
Classifier: Development Status :: 5 - Production/Stable
Requires-Python: >= 3.6
